st_stripe/__init__.py
st_stripe/aggregate_auth.py
st_stripe/google_auth.py
st_stripe/stripe_auth.py
st_stripe-0.1.4.dist-info/METADATA
st_stripe-0.1.4.dist-info/WHEEL
st_stripe-0.1.4.dist-info/top_level.txt
st_stripe-0.1.4.dist-info/RECORD
