Metadata-Version: 2.1
Name: st-stripe
Version: 0.1.4
Summary: A Python package for creating subscription Streamlit apps
Author-email: Tyler <tylerjrichards@gmail.com>
License: MIT
Requires-Dist: stripe
Requires-Dist: httpx-oauth
Requires-Dist: pyjwt
